random_word_numpy/__init__.py
random_word_numpy/random_word.py
random_word_numpy/database/words.json
random_word_numpy/tests/__init__.py
random_word_numpy/tests/test_random_word.py
random_word_numpy-0.0.2.dist-info/LICENSE
random_word_numpy-0.0.2.dist-info/METADATA
random_word_numpy-0.0.2.dist-info/WHEEL
random_word_numpy-0.0.2.dist-info/top_level.txt
random_word_numpy-0.0.2.dist-info/RECORD
