Metadata-Version: 2.1
Name: random-word-numpy
Version: 0.0.2
Summary: This is a simple python package to generate random english words
Home-page: https://github.com/bschreck/random-word-numpy
Author: Ben Schreck <ben@benschreck.com>
Author-email: ben@benschreck.com
License: MIT
Keywords: package random words word of the day random word generator
Classifier: Programming Language :: Python
Classifier: Programming Language :: Python :: 3
Classifier: Programming Language :: Python :: 3.1
Classifier: Programming Language :: Python :: 3.2
Classifier: Programming Language :: Python :: 3.3
Classifier: Programming Language :: Python :: 3.4
Classifier: Programming Language :: Python :: 3.5
Classifier: Programming Language :: Python :: 3.6
Classifier: Programming Language :: Python :: 3.7
Classifier: Programming Language :: Python :: 3.8
Classifier: Programming Language :: Python :: 3.9
Classifier: Programming Language :: Python :: 3.10
Classifier: License :: OSI Approved :: MIT License
Classifier: Operating System :: OS Independent
Requires-Python: >=3
License-File: LICENSE
Requires-Dist: requests
Requires-Dist: pytest
Requires-Dist: pyyaml
